LICENSE.txt
MANIFEST.in
README.rst
setup.py
fio_buffer/__init__.py
fio_buffer/core.py
fio_buffer.egg-info/PKG-INFO
fio_buffer.egg-info/SOURCES.txt
fio_buffer.egg-info/dependency_links.txt
fio_buffer.egg-info/entry_points.txt
fio_buffer.egg-info/requires.txt
fio_buffer.egg-info/top_level.txt
fio_buffer.egg-info/zip-safe
tests/__init__.py
tests/test_cli.py
tests/test_cli_callbacks.py
tests/test_exceptions.py
tests/test_processor.py