Metadata-Version: 1.1
Name: fio-buffer
Version: 0.1.1
Summary: A Fiona CLI plugin for buffering geometries.
Home-page: https://github.com/geowurster/fio-buffer
Author: Kevin Wurster
Author-email: wursterk@gmail.com
License: New BSD
Keywords: Fiona fio GIS vector buffer plugin
Platform: UNKNOWN
Classifier: Development Status :: 4 - Beta
Classifier: Intended Audience :: Developers
Classifier: Intended Audience :: Information Technology
Classifier: Intended Audience :: Science/Research
Classifier: License :: OSI Approved :: BSD License
Classifier: Programming Language :: Python :: 2.7
Classifier: Programming Language :: Python :: 3.3
Classifier: Programming Language :: Python :: 3.4
Classifier: Topic :: Scientific/Engineering :: GIS
